{
  "version": 1,
  "categoryId": "spring-boot",
  "subcategoryId": "spring-security",
  "id": "spring-security-interview-4",
  "title": "Spring Security Interview - 4",
  "description": "JWT yapisi, claimler, imza algoritmalari ve token validation kurallari",
  "questions": [
    {
      "id": "i4-q1",
      "type": "mcq",
      "questionKind": "direct",
      "singleChoice": true,
      "question": "JWTnin uc parcasi dogru olarak hangisidir?",
      "choices": [
        {
          "id": "A",
          "text": "header.body.footer"
        },
        {
          "id": "B",
          "text": "request.payload.response"
        },
        {
          "id": "C",
          "text": "header.payload.signature"
        },
        {
          "id": "D",
          "text": "algorithm.claims.session"
        }
      ],
      "correctChoiceIds": [
        "C"
      ],
      "questionCode": null,
      "answerBody": "",
      "optionExplanations": [],
      "answerCode": ""
    },
    {
      "id": "i4-q2",
      "type": "mcq",
      "questionKind": "direct",
      "singleChoice": true,
      "question": "JWT signature neyi garanti eder?",
      "choices": [
        {
          "id": "A",
          "text": "Payloadin gizli oldugunu garanti eder."
        },
        {
          "id": "B",
          "text": "Tokenin degistirilmedigini (integrity) ve imzayi ureten kaynaga guveni destekler."
        },
        {
          "id": "C",
          "text": "Tokenin hicbir zaman expire olmayacagini garanti eder."
        },
        {
          "id": "D",
          "text": "Kullanicinin her zaman ADMIN oldugunu garanti eder."
        }
      ],
      "correctChoiceIds": [
        "B"
      ],
      "questionCode": null,
      "answerBody": "",
      "optionExplanations": [],
      "answerCode": ""
    },
    {
      "id": "i4-q3",
      "type": "mcq",
      "questionKind": "direct",
      "singleChoice": true,
      "question": "exp claiminin anlami nedir?",
      "choices": [
        {
          "id": "A",
          "text": "Tokenin olusturuldugu an"
        },
        {
          "id": "B",
          "text": "Tokenin gecersiz olacagi son an"
        },
        {
          "id": "C",
          "text": "Kullanici rol listesi"
        },
        {
          "id": "D",
          "text": "JWT algoritma tipi"
        }
      ],
      "correctChoiceIds": [
        "B"
      ],
      "questionCode": null,
      "answerBody": "",
      "optionExplanations": [],
      "answerCode": ""
    },
    {
      "id": "i4-q4",
      "type": "mcq",
      "questionKind": "direct",
      "singleChoice": true,
      "question": "Asagidakilerden hangisi JWT payload icin dogru bir guvenlik notudur?",
      "choices": [
        {
          "id": "A",
          "text": "Payload defaultta sifrelidir, kimse okuyamaz."
        },
        {
          "id": "B",
          "text": "Payload base64url encoded oldugu icin okunabilir; gizli bilgi koymamak gerekir."
        },
        {
          "id": "C",
          "text": "Payload sadece server tarafindan okunur, client gormez."
        },
        {
          "id": "D",
          "text": "Payload sadece ADMIN rolu icin vardir."
        }
      ],
      "correctChoiceIds": [
        "B"
      ],
      "questionCode": null,
      "answerBody": "",
      "optionExplanations": [],
      "answerCode": ""
    },
    {
      "id": "i4-q5",
      "type": "mcq",
      "questionKind": "direct",
      "singleChoice": true,
      "question": "HS256 ve RS256 farki icin dogru ifade hangisidir?",
      "choices": [
        {
          "id": "A",
          "text": "HS256 tek secret ile simetrik imzalama, RS256 private/public key ile asimetrik imzalama kullanir."
        },
        {
          "id": "B",
          "text": "Ikisi tamamen ayni sekilde calisir."
        },
        {
          "id": "C",
          "text": "RS256 sadece cookie tabanli auth icindir."
        },
        {
          "id": "D",
          "text": "HS256da imza yoktur."
        }
      ],
      "correctChoiceIds": [
        "A"
      ],
      "questionCode": null,
      "answerBody": "Doğru cevap: **HS256 tek secret ile simetrik imzalama, RS256 private/public key ile asimetrik imzalama kullanir.**\n\nBu iki algoritma arasındaki fark, modern sistemlerin güvenliğini ve ölçeklenebilirliğini doğrudan etkiler. İşte detaylı ve örnekli karşılaştırma:\n\n---\n\n### 1. HS256 (HMAC with SHA-256) - Simetrik\nBu yöntemde tek bir **\"Secret Key\"** vardır. Bu anahtar hem token’ı imzalamak için hem de doğrulamak için kullanılır.\n\n* **Çalışma Mantığı:** Evindeki tek bir anahtar gibi düşün; kapıyı hem o anahtarla kilitlersin hem de o anahtarla açarsın.\n* **Kullanım:** Eğer token’ı üreten (Auth Service) ve token’ı kontrol eden (Resource Service) aynı uygulama ise veya bu iki servis aynı gizli anahtarı güvenle paylaşabiliyorsa kullanılır.\n* **Risk:** Eğer bu gizli anahtar çalınırsa, saldırgan hem senin adına token üretebilir hem de mevcut olanları doğrulayabilir.\n\n\n\n---\n\n### 2. RS256 (RSA Signature with SHA-256) - Asimetrik\nBu yöntemde bir **Anahtar Çifti (Key Pair)** vardır: **Private Key** (Gizli) ve **Public Key** (Açık).\n\n* **Çalışma Mantığı:** Bir asma kilit gibi düşün. **Private Key** sadece sendedir (Auth Service) ve token’ı \"kilitlemek\" (imzalamak) için kullanılır. **Public Key** ise herkese dağıtılabilir; sadece kilidin (imzanın) doğru olup olmadığını kontrol etmeye yarar ama yeni bir kilit üretemez.\n* **Kullanım:** Mikroservis mimarilerinde veya Google/Facebook gibi dış kaynaklı login sistemlerinde (OAuth2/OpenID Connect) standarttır.\n* **Avantaj:** Diğer servislerin (Microservices) sadece Public Key'e sahip olması yeterlidir. Bu servislerin güvenliği ihlal edilse bile, saldırgan senin adına sahte token üretemez (çünkü Private Key hala sende güvende).\n\n\n\n---\n\n### Karşılaştırma Tablosu\n\n| Özellik | HS256 | RS256 |\n| :--- | :--- | :--- |\n| **Anahtar Tipi** | Tek bir Gizli Anahtar (Shared Secret) | Private + Public Key |\n| **Güvenlik Modeli** | Simetrik | Asimetrik |\n| **Hız** | Daha hızlı (Matematiksel olarak basit) | Biraz daha yavaş (Matematiksel yükü fazla) |\n| **Senaryo** | Tekil uygulamalar (Monolith) | Mikroservisler, SSO, Üçüncü parti sistemler |\n\n---\n\n### Özetle\n* **HS256'da:** \"Bu anahtarı bilen herkes imza atabilir.\"\n* **RS256'da:** \"Sadece ben imza atabilirim, ama herkes imzamın bana ait olduğunu teyit edebilir.\"\n\nŞu an geliştirdiğin yapıda (Spring Boot + React), eğer sadece tek bir backend servisin varsa **HS256** işini fazlasıyla görecektir. Ancak ileride mikroservis mimarisine geçmeyi planlıyorsan **RS256** öğrenmek iyi bir yatırım olur. Hangi yapı sana daha güvenli geliyor?\n",
      "optionExplanations": [],
      "answerCode": ""
    },
    {
      "id": "i4-q6",
      "type": "mcq",
      "questionKind": "direct",
      "singleChoice": true,
      "question": "Claim tasariminda en saglikli yaklasim hangisidir?",
      "choices": [
        {
          "id": "A",
          "text": "Tokeni olabildigince buyutmek, tum profil datasini koymak"
        },
        {
          "id": "B",
          "text": "Kimlik/yetki icin gerekli minimal claimleri koymak, hassas veriyi tokena koymamak"
        },
        {
          "id": "C",
          "text": "Her claimi encrypted oldugu varsayimiyla saklamak"
        },
        {
          "id": "D",
          "text": "exp claimini hic koymamak"
        }
      ],
      "correctChoiceIds": [
        "B"
      ],
      "questionCode": null,
      "answerBody": "",
      "optionExplanations": [],
      "answerCode": ""
    },
    {
      "id": "i4-q7",
      "type": "mcq",
      "questionKind": "direct",
      "singleChoice": true,
      "question": "JWT validationda asagidakilerden hangisi eksik bir yaklasimdir?",
      "choices": [
        {
          "id": "A",
          "text": "Sadece expiration kontrol edip signature kontrolu yapmamak"
        },
        {
          "id": "B",
          "text": "Signature + exp + issuer gibi kontrolleri birlikte yapmak"
        },
        {
          "id": "C",
          "text": "Token subjectini beklenen userla karsilastirmak"
        },
        {
          "id": "D",
          "text": "Clock skew toleransi dusunmek"
        }
      ],
      "correctChoiceIds": [
        "A"
      ],
      "questionCode": null,
      "answerBody": "",
      "optionExplanations": [],
      "answerCode": ""
    },
    {
      "id": "i4-q8",
      "type": "mcq",
      "questionKind": "code-output",
      "singleChoice": true,
      "question": "Bu kodla ilgili en dogru yorum hangisidir?",
      "choices": [
        {
          "id": "A",
          "text": "true ise token en azindan exp ve signature kontrollerini gecmis olmalidir."
        },
        {
          "id": "B",
          "text": "true olsa bile token kesinlikle hicbir sekilde revoke edilemez."
        },
        {
          "id": "C",
          "text": "Bu kod CSRFu otomatik cozer."
        },
        {
          "id": "D",
          "text": "Bu kod compile olmaz."
        }
      ],
      "correctChoiceIds": [
        "A"
      ],
      "questionCode": "boolean valid = jwtService.isTokenValid(token, userDetails);\nif (!valid) {\n    response.setStatus(401);\n}",
      "answerBody": "Basit, güvenli ve standartlara uygun bir `JwtService` sınıfını aşağıda bulabilirsin. Bu örnekte `jjwt` (Java JWT) kütüphanesini baz alıyoruz.\n\n```java\nimport io.jsonwebtoken.Claims;\nimport io.jsonwebtoken.Jwts;\nimport io.jsonwebtoken.SignatureAlgorithm;\nimport io.jsonwebtoken.io.Decoders;\nimport io.jsonwebtoken.security.Keys;\nimport org.springframework.security.core.userdetails.UserDetails;\nimport org.springframework.stereotype.Service;\n\nimport java.security.Key;\nimport java.util.Date;\nimport java.util.HashMap;\nimport java.util.Map;\nimport java.util.function.Function;\n\n@Service\npublic class JwtService {\n\n    // Gerçek uygulamada bu değeri Kubernetes Secret veya Vault'tan almalısın!\n    private static final String SECRET_KEY = \"404E635266556A586E3272357538782F413F4428472B4B6250645367566B5970\";\n\n    /**\n     * Token üretme metodu.\n     */\n    public String generateToken(String subject, Map<String, Object> authorities) {\n        return Jwts.builder()\n                .setClaims(authorities) // Roller vb.\n                .setSubject(subject)    // Genellikle email/username\n                .setIssuedAt(new Date(System.currentTimeMillis()))\n                .setExpiration(new Date(System.currentTimeMillis() + 1000 * 60 * 60 * 24)) // 24 Saat\n                .signWith(getSignInKey(), SignatureAlgorithm.HS256)\n                .compact();\n    }\n\n    /**\n     * Token doğruluğunu kontrol eder (Subject, Expiration ve Signature).\n     */\n    public boolean isTokenValid(String token, UserDetails userDetails) {\n        final String username = extractUsername(token);\n        // 1. Subject kontrolü: Token'daki isim DB'dekiyle aynı mı?\n        // 2. Expiration kontrolü: Token'ın süresi dolmuş mu?\n        // (Signature kontrolü zaten extractClaim sırasında kütüphane tarafından otomatik yapılır)\n        return (username.equals(userDetails.getUsername())) && !isTokenExpired(token);\n    }\n\n    public String extractUsername(String token) {\n        return extractClaim(token, Claims::getSubject);\n    }\n\n    private boolean isTokenExpired(String token) {\n        return extractExpiration(token).before(new Date());\n    }\n\n    private Date extractExpiration(String token) {\n        return extractClaim(token, Claims::getExpiration);\n    }\n\n    // --- JWT Yardımcı Metotları ---\n\n    public <T> T extractClaim(String token, Function<Claims, T> claimsResolver) {\n        final Claims claims = extractAllClaims(token);\n        return claimsResolver.apply(claims);\n    }\n\n    private Claims extractAllClaims(String token) {\n        // Bu metod imzayı (Signature) kontrol eder. \n        // Eğer imza hatalıysa io.jsonwebtoken.security.SignatureException fırlatır.\n        return Jwts.parserBuilder()\n                .setSigningKey(getSignInKey())\n                .build()\n                .parseClaimsJws(token)\n                .getBody();\n    }\n\n    private Key getSignInKey() {\n        byte[] keyBytes = Decoders.BASE64.decode(SECRET_KEY);\n        return Keys.hmacShaKeyFor(keyBytes);\n    }\n}\n```\n\n---\n\n### Bu Kod Neleri Garanti Altına Alır?\n\n1.  **Signature (İmza) Kontrolü:** `extractAllClaims` içindeki `setSigningKey` kısmı, token yolda birisi tarafından değiştirilmişse (Payload manipülasyonu) anında hata fırlatır. Yani \"İmza doğru değilse içeri giremezsin\" kuralı burada çalışır.\n2.  **Expiration (Süre) Kontrolü:** `isTokenExpired` metodu, token'ın içindeki `exp` değerine bakar. Süre geçmişse `isTokenValid` doğrudan `false` döner.\n3.  **Subject (Kimlik) Kontrolü:** Token içindeki `sub` alanının, veritabanından çektiğimiz `UserDetails` ile eşleşip eşleşmediğine bakar.\n4.  **Claims (Yetkiler):** `generateToken` içine geçtiğin `authorities` map'i sayesinde, token çözüldüğünde kullanıcının rollerini de içinden çekebilirsin.\n\n\n\n### Önemli Bir Detay:\nFark ettiysen `isTokenValid` metoduna `UserDetails` nesquesini dışarıdan geçiyoruz. Bir önceki sorunda konuştuğumuz gibi; filtre önce token'dan ismi çeker, sonra o isimle DB'den `UserDetails`'i yükler ve son onay için bu metoda gönderir.\n\nBu yapı senin için yeterince sade mi, yoksa bazı kısımları (örneğin Claims çıkarma) daha detaylı inceleyelim mi?\n",
      "optionExplanations": [],
      "answerCode": ""
    },
    {
      "id": "i4-q9",
      "type": "mcq",
      "questionKind": "code-output",
      "singleChoice": true,
      "question": "Asagidaki akista 20 dakika sonra en olasi sonuc nedir?",
      "choices": [
        {
          "id": "A",
          "text": "Token hala gecerlidir cunku iat var."
        },
        {
          "id": "B",
          "text": "exp now+15m ise 20 dakika sonra token gecersiz kabul edilir."
        },
        {
          "id": "C",
          "text": "Token sure kontrolu algoritmadan bagimsizdir, her zaman gecerli kalir."
        },
        {
          "id": "D",
          "text": "Kod sadece role kontrolu yapar."
        }
      ],
      "correctChoiceIds": [
        "B"
      ],
      "questionCode": "Instant now = Instant.now();\nString token = jwtService.generateToken(subject, now.plus(15, ChronoUnit.MINUTES));\n// 20 dakika sonra validate(token)",
      "answerBody": "",
      "optionExplanations": [],
      "answerCode": ""
    },
    {
      "id": "i4-q10",
      "type": "code",
      "question": "Basit bir JwtService yaz: generateToken(subject, authorities) ve isTokenValid(token, userDetails) metotlarini icersin. exp, subject ve signature kontrolu yap.",
      "starterCode": "class JwtService {\n    // TODO\n}",
      "answerCode": "class JwtService {\n    private final Key signingKey;\n\n    JwtService(Key signingKey) {\n        this.signingKey = signingKey;\n    }\n\n    String generateToken(String subject, List<String> authorities) {\n        Instant now = Instant.now();\n        return Jwts.builder()\n            .subject(subject)\n            .claim(\"authorities\", authorities)\n            .issuedAt(Date.from(now))\n            .expiration(Date.from(now.plus(15, ChronoUnit.MINUTES)))\n            .signWith(signingKey)\n            .compact();\n    }\n\n    boolean isTokenValid(String token, UserDetails userDetails) {\n        Claims claims = Jwts.parser().verifyWith((SecretKey) signingKey).build()\n            .parseSignedClaims(token).getPayload();\n\n        String subject = claims.getSubject();\n        Date exp = claims.getExpiration();\n        return userDetails.getUsername().equals(subject) && exp.after(new Date());\n    }\n}",
      "answerBody": "### Dogru Cevap\nAsagidaki referans kodu inceleyebilirsin.",
      "optionExplanations": []
    }
  ]
}
